swelldb/__init__.py
swelldb/catalog.py
swelldb/swelldb.py
swelldb/datasource/__init__.py
swelldb/datasource/database_datasource.py
swelldb/datasource/datasource.py
swelldb/datasource/local_csv_datasource.py
swelldb/datasource/sqlite_datasource.py
swelldb/engine/__init__.py
swelldb/engine/datafusion_processor.py
swelldb/engine/execution_engine.py
swelldb/llm/__init__.py
swelldb/llm/abstract_llm.py
swelldb/llm/deepseek_llm.py
swelldb/llm/ollama_llm.py
swelldb/llm/openai_llm.py
swelldb/prompt/__init__.py
swelldb/prompt/prompt_utils.py
swelldb/table_plan/__init__.py
swelldb/table_plan/layout.py
swelldb/table_plan/planner.py
swelldb/table_plan/planner_prompts.py
swelldb/table_plan/swelldb_attribute.py
swelldb/table_plan/swelldb_schema.py
swelldb/table_plan/prompts/__init__.py
swelldb/table_plan/prompts/dataset_table_columns_prompt.jinja
swelldb/table_plan/prompts/llm_table_columns_prompt.jinja
swelldb/table_plan/prompts/llm_table_prompt.jinja
swelldb/table_plan/prompts/search_engine_columns_prompt.jinja
swelldb/table_plan/prompts/search_engine_prompt.jinja
swelldb/table_plan/prompts/table_columns_prompt.jinja
swelldb/table_plan/prompts/table_prompt.jinja
swelldb/table_plan/table/__init__.py
swelldb/table_plan/table/logical/__init__.py
swelldb/table_plan/table/logical/logical_table.py
swelldb/table_plan/table/physical/__init__.py
swelldb/table_plan/table/physical/custom_table.py
swelldb/table_plan/table/physical/database_table.py
swelldb/table_plan/table/physical/dataset_table.py
swelldb/table_plan/table/physical/document_table.py
swelldb/table_plan/table/physical/llm_table.py
swelldb/table_plan/table/physical/physical_table.py
swelldb/table_plan/table/physical/search_engine_table.py
swelldb/util/__init__.py
swelldb/util/config_parser.py
swelldb/util/globals.py
swelldb-0.1.2.dist-info/licenses/LICENSE
swelldb-0.1.2.dist-info/METADATA
swelldb-0.1.2.dist-info/WHEEL
swelldb-0.1.2.dist-info/top_level.txt
swelldb-0.1.2.dist-info/RECORD
