Metadata-Version: 2.4
Name: swelldb
Version: 0.1.2
Summary: Dynamic Query-Driven Table Generation with LLMs
Author-email: Victor Giannakouris <giannakouris.victor@gmail.com>
License: MIT License
Project-URL: Homepage, https://github.com/SwellDB/SwellDB
Project-URL: Repository, https://github.com/SwellDB/SwellDB
Project-URL: Issues, https://github.com/SwellDB/SwellDB/issues
Requires-Python: >=3.10
License-File: LICENSE
Requires-Dist: pandas
Requires-Dist: pyarrow
Requires-Dist: datafusion
Requires-Dist: langchain-core
Requires-Dist: langchain-community
Requires-Dist: langchain-openai
Requires-Dist: jinja2
Requires-Dist: overrides
Dynamic: license-file
